harlogger/__init__.py
harlogger/__main__.py
harlogger/_version.py
harlogger/exceptions.py
harlogger/haralyzer_patches.py
harlogger/http_transaction.py
harlogger/sniffers.py
src/Makefile
src/control
src/entitlements.plist
src/main.m
src/bin/harlogger
src/packages/com.cyber.har-logger_0.0.1-14+debug_iphoneos-arm.deb
harlogger-4.0.3.dist-info/LICENSE
harlogger-4.0.3.dist-info/METADATA
harlogger-4.0.3.dist-info/WHEEL
harlogger-4.0.3.dist-info/entry_points.txt
harlogger-4.0.3.dist-info/top_level.txt
harlogger-4.0.3.dist-info/RECORD
