Metadata-Version: 2.1
Name: harlogger
Version: 4.0.3
Summary: Simple utlity for sniffing decrypted HTTP/HTTPS traffic on an iOS device (either jailbroken or not)
Author-email: doronz88 <doron88@gmail.com>, netanelc305 <netanelc305@protonmail.com>
Maintainer-email: doronz88 <doron88@gmail.com>, netanelc305 <netanelc305@protonmail.com>
License: GNU GENERAL PUBLIC LICENSE
Project-URL: Homepage, https://github.com/doronz88/harlogger
Project-URL: Bug Reports, https://github.com/doronz88/harlogger/issues
Keywords: ios,osx,mac,macos,http,https,har,sniffer,jailbroken
Classifier: Development Status :: 5 - Production/Stable
Classifier: License :: OSI Approved :: GNU General Public License v3 or later (GPLv3+)
Classifier: Programming Language :: Python :: 3
Classifier: Programming Language :: Python :: 3.8
Classifier: Programming Language :: Python :: 3.9
Classifier: Programming Language :: Python :: 3.10
Classifier: Programming Language :: Python :: 3.11
Classifier: Programming Language :: Python :: 3 :: Only
Requires-Python: >=3.8
License-File: LICENSE
Requires-Dist: click
Requires-Dist: pymobiledevice3 >=2.0.2
Requires-Dist: pygments
Requires-Dist: haralyzer >=2.4.0
Requires-Dist: maclog
Provides-Extra: test
Requires-Dist: pytest ; extra == 'test'
